[{"id":"SPC-G-01-WS","roomName":"Weights Section","capacity":25,"occupied":20,"hasSubtype":false,"occupiedBy":"Students","roomType":"Gym Area","floor":"ground","status":"Partially Allocated","roomArea":"150","buildingId":"SPC","parentId":"SPC-G-01","managedBy":"Central facilities"},{"id":"SPC-G-01-CA","roomName":"Cardio Area","capacity":30,"occupied":25,"hasSubtype":false,"occupiedBy":"Students","roomType":"Gym Area","floor":"ground","status":"Partially Allocated","roomArea":"150","buildingId":"SPC","parentId":"SPC-G-01","managedBy":"Academic"},{"id":"SPC-G-01-YC","roomName":"Yoga/Stretching Corner","capacity":15,"occupied":5,"hasSubtype":false,"occupiedBy":"Students","roomType":"Workout Zone","floor":"ground","status":"Partially Allocated","roomArea":"50","buildingId":"SPC","parentId":"SPC-G-01","managedBy":"Academic"},{"id":"SPC-G-01-MS","roomName":"Main Sports Hall","capacity":30,"occupied":10,"hasSubtype":false,"occupiedBy":"Sports Team","roomType":"Court","floor":"ground","status":"Partially Allocated","roomArea":"150","buildingId":"SPC","parentId":"SPC-G-01","managedBy":"Central facilities"},{"id":"AB1-G-04-SA","roomName":"Main Seating Area","capacity":100,"occupied":0,"hasSubtype":false,"occupiedBy":null,"roomType":"Seating Area","floor":"ground","status":"Available","roomArea":"120","buildingId":"AB1","parentId":"AB1-G-04","managedBy":"Central facilities"},{"id":"AB1-G-04-STG","roomName":"Stage","capacity":5,"occupied":0,"hasSubtype":false,"occupiedBy":null,"roomType":"Presentation Stage","floor":"ground","status":"Available","roomArea":"20","buildingId":"AB1","parentId":"AB1-G-04","managedBy":"Central facilities"},{"id":"AB1-G-04-CR","roomName":"Control Room","capacity":2,"occupied":0,"hasSubtype":false,"occupiedBy":null,"roomType":"Utility","floor":"ground","status":"Available","roomArea":"10","buildingId":"AB1","parentId":"AB1-G-04","managedBy":"Central facilities"},{"id":"LB1-G-01-SC1","roomName":"Study Carrel 1","capacity":1,"occupied":1,"hasSubtype":false,"occupiedBy":"Student","roomType":"Study Carrel","floor":"ground","status":"Allocated","roomArea":"2","buildingId":"LB1","parentId":"LB1-G-01","managedBy":"Academic"},{"id":"LB1-G-01-SC2","roomName":"Study Carrel 2","capacity":1,"occupied":1,"hasSubtype":false,"occupiedBy":"Student","roomType":"Study Carrel","floor":"ground","status":"Allocated","roomArea":"2","buildingId":"LB1","parentId":"LB1-G-01","managedBy":"Academic"},{"id":"LB1-G-01-SC3","roomName":"Study Carrel 3","capacity":1,"occupied":0,"hasSubtype":false,"occupiedBy":null,"roomType":"Study Carrel","floor":"ground","status":"Available","roomArea":"2","buildingId":"LB1","parentId":"LB1-G-01","managedBy":"Academic"},{"id":"LB1-G-01-LW1","roomName":"Librarian Workstation 1","capacity":1,"occupied":1,"hasSubtype":false,"occupiedBy":"Librarian","roomType":"Workstation","floor":"ground","status":"Allocated","roomArea":"5","buildingId":"LB1","parentId":"LB1-G-01","managedBy":"Academic"},{"id":"LB1-G-01-LW2","roomName":"Librarian Workstation 2","capacity":1,"occupied":1,"hasSubtype":false,"occupiedBy":"Librarian","roomType":"Workstation","floor":"ground","status":"Allocated","roomArea":"5","buildingId":"LB1","parentId":"LB1-G-01","managedBy":"Academic"},{"id":"LB1-G-01-QA","roomName":"Quiet Study Area","capacity":20,"occupied":15,"hasSubtype":false,"occupiedBy":null,"roomType":"Reading Area","floor":"ground","status":"Partially Allocated","roomArea":"50","buildingId":"LB1","parentId":"LB1-G-01","managedBy":"Academic"},{"id":"AB2-F1-04-MA","roomName":"Main Meeting Area","capacity":8,"occupied":0,"hasSubtype":false,"occupiedBy":null,"roomType":"Meeting Area","floor":"first","status":"Available","roomArea":"35","buildingId":"AB2","parentId":"AB2-F1-04","managedBy":"Central facilities"},{"id":"AB2-F1-04-AV","roomName":"AV Console","capacity":1,"occupied":0,"hasSubtype":false,"occupiedBy":null,"roomType":"Utility","floor":"first","status":"Available","roomArea":"5","buildingId":"AB2","parentId":"AB2-F1-04","managedBy":"Academic"},{"id":"AB1-G-02-WS1","roomName":"Workstation 1","capacity":1,"occupied":1,"hasSubtype":false,"occupiedBy":"Student 1","roomType":"Workstation","floor":"ground","status":"Allocated","roomArea":"3","buildingId":"AB1","parentId":"AB1-G-02","managedBy":"Central facilities"},{"id":"AB1-G-02-WS2","roomName":"Workstation 2","capacity":1,"occupied":1,"hasSubtype":false,"occupiedBy":"Student 2","roomType":"Workstation","floor":"ground","status":"Allocated","roomArea":"3","buildingId":"AB1","parentId":"AB1-G-02","managedBy":"Academic"},{"id":"AB1-G-02-WS3","roomName":"Workstation 3","capacity":1,"occupied":1,"hasSubtype":false,"occupiedBy":"Student 3","roomType":"Workstation","floor":"ground","status":"Allocated","roomArea":"3","buildingId":"AB1","parentId":"AB1-G-02","managedBy":"Academic"},{"id":"AB1-G-02-WS4","roomName":"Workstation 4","capacity":1,"occupied":1,"hasSubtype":false,"occupiedBy":"Student 4","roomType":"Workstation","floor":"ground","status":"Allocated","roomArea":"3","buildingId":"AB1","parentId":"AB1-G-02","managedBy":"Academic"},{"id":"AB1-G-02-WS5","roomName":"Workstation 5","capacity":1,"occupied":1,"hasSubtype":false,"occupiedBy":"Student 5","roomType":"Workstation","floor":"ground","status":"Allocated","roomArea":"3","buildingId":"AB1","parentId":"AB1-G-02","managedBy":"Academic"},{"id":"AB1-G-02-WS6","roomName":"Workstation 6","capacity":1,"occupied":1,"hasSubtype":false,"occupiedBy":"Student 6","roomType":"Workstation","floor":"ground","status":"Allocated","roomArea":"3","buildingId":"AB1","parentId":"AB1-G-02","managedBy":"Academic"},{"id":"AD0-F1-01-C1","roomName":"HR Manager's Cabin","capacity":1,"occupied":1,"hasSubtype":false,"occupiedBy":"HR Manager","roomType":"Cabin","floor":"first","status":"Allocated","roomArea":"15","buildingId":"AD0","parentId":"AD0-F1-01","managedBy":"Central facilities"},{"id":"AD0-F1-01-C2","roomName":"HR Analyst Workstation 1","capacity":1,"occupied":1,"hasSubtype":false,"occupiedBy":"HR Analyst 1","roomType":"Workstation","floor":"first","status":"Allocated","roomArea":"10","buildingId":"AD0","parentId":"AD0-F1-01","managedBy":"Academic"},{"id":"AD0-F1-01-C3","roomName":"HR Analyst Workstation 2","capacity":1,"occupied":1,"hasSubtype":false,"occupiedBy":"HR Analyst 2","roomType":"Workstation","floor":"first","status":"Allocated","roomArea":"10","buildingId":"AD0","parentId":"AD0-F1-01","managedBy":"Academic"},{"id":"AD0-F1-01-C4","roomName":"HR Workstation 3","capacity":1,"occupied":1,"hasSubtype":false,"occupiedBy":"HR Intern","roomType":"Workstation","floor":"first","status":"Allocated","roomArea":"10","buildingId":"AD0","parentId":"AD0-F1-01","managedBy":"Academic"},{"id":"AD0-F1-01-MTG","roomName":"Internal Meeting Area","capacity":6,"occupied":2,"hasSubtype":false,"occupiedBy":null,"roomType":"Meeting Area","floor":"first","status":"Partially Allocated","roomArea":"20","buildingId":"AD0","parentId":"AD0-F1-01","managedBy":"Central facilities"}]